[
    {
        "name": "id",
        "dbType": "string",
        "htmlType": "text",
        "validations": "",
        "searchable": false,
        "fillable": false,
        "primary": true,
        "inForm": false,
        "inIndex": false,
        "inView": false
    },
    {
        "name": "IncentivesId",
        "dbType": "string",
        "htmlType": "text",
        "validations": "nullable|string|max:60|nullable|string|max:60",
        "searchable": true,
        "fillable": true,
        "primary": false,
        "inForm": true,
        "inIndex": true,
        "inView": true
    },
    {
        "name": "EmployeeId",
        "dbType": "string",
        "htmlType": "text",
        "validations": "nullable|string|max:50|nullable|string|max:50",
        "searchable": true,
        "fillable": true,
        "primary": false,
        "inForm": true,
        "inIndex": true,
        "inView": true
    },
    {
        "name": "FourteenthMonthPay",
        "dbType": "decimal",
        "htmlType": "number",
        "validations": "nullable|numeric|nullable|numeric",
        "searchable": true,
        "fillable": true,
        "primary": false,
        "inForm": true,
        "inIndex": true,
        "inView": true
    },
    {
        "name": "ThirteenthMonthDifferential",
        "dbType": "decimal",
        "htmlType": "number",
        "validations": "nullable|numeric|nullable|numeric",
        "searchable": true,
        "fillable": true,
        "primary": false,
        "inForm": true,
        "inIndex": true,
        "inView": true
    },
    {
        "name": "CashGift",
        "dbType": "decimal",
        "htmlType": "number",
        "validations": "nullable|numeric|nullable|numeric",
        "searchable": true,
        "fillable": true,
        "primary": false,
        "inForm": true,
        "inIndex": true,
        "inView": true
    },
    {
        "name": "VacationLeave",
        "dbType": "decimal",
        "htmlType": "number",
        "validations": "nullable|numeric|nullable|numeric",
        "searchable": true,
        "fillable": true,
        "primary": false,
        "inForm": true,
        "inIndex": true,
        "inView": true
    },
    {
        "name": "SickLeave",
        "dbType": "decimal",
        "htmlType": "number",
        "validations": "nullable|numeric|nullable|numeric",
        "searchable": true,
        "fillable": true,
        "primary": false,
        "inForm": true,
        "inIndex": true,
        "inView": true
    },
    {
        "name": "LoyaltyAward",
        "dbType": "decimal",
        "htmlType": "number",
        "validations": "nullable|numeric|nullable|numeric",
        "searchable": true,
        "fillable": true,
        "primary": false,
        "inForm": true,
        "inIndex": true,
        "inView": true
    },
    {
        "name": "SubTotal",
        "dbType": "decimal",
        "htmlType": "number",
        "validations": "nullable|numeric|nullable|numeric",
        "searchable": true,
        "fillable": true,
        "primary": false,
        "inForm": true,
        "inIndex": true,
        "inView": true
    },
    {
        "name": "AROthers",
        "dbType": "decimal",
        "htmlType": "number",
        "validations": "nullable|numeric|nullable|numeric",
        "searchable": true,
        "fillable": true,
        "primary": false,
        "inForm": true,
        "inIndex": true,
        "inView": true
    },
    {
        "name": "BEMPC",
        "dbType": "decimal",
        "htmlType": "number",
        "validations": "nullable|numeric|nullable|numeric",
        "searchable": true,
        "fillable": true,
        "primary": false,
        "inForm": true,
        "inIndex": true,
        "inView": true
    },
    {
        "name": "WithholdingTaxes",
        "dbType": "decimal",
        "htmlType": "number",
        "validations": "nullable|numeric|nullable|numeric",
        "searchable": true,
        "fillable": true,
        "primary": false,
        "inForm": true,
        "inIndex": true,
        "inView": true
    },
    {
        "name": "NetPay",
        "dbType": "decimal",
        "htmlType": "number",
        "validations": "nullable|numeric|nullable|numeric",
        "searchable": true,
        "fillable": true,
        "primary": false,
        "inForm": true,
        "inIndex": true,
        "inView": true
    },
    {
        "name": "UserId",
        "dbType": "string",
        "htmlType": "text",
        "validations": "nullable|string|max:50|nullable|string|max:50",
        "searchable": true,
        "fillable": true,
        "primary": false,
        "inForm": true,
        "inIndex": true,
        "inView": true
    },
    {
        "name": "EmployeeType",
        "dbType": "string",
        "htmlType": "text",
        "validations": "nullable|string|max:50|nullable|string|max:50",
        "searchable": true,
        "fillable": true,
        "primary": false,
        "inForm": true,
        "inIndex": true,
        "inView": true
    },
    {
        "name": "Department",
        "dbType": "string",
        "htmlType": "text",
        "validations": "nullable|string|max:50|nullable|string|max:50",
        "searchable": true,
        "fillable": true,
        "primary": false,
        "inForm": true,
        "inIndex": true,
        "inView": true
    },
    {
        "name": "created_at",
        "dbType": "datetime",
        "htmlType": "date",
        "validations": "nullable|nullable",
        "searchable": false,
        "fillable": false,
        "primary": false,
        "inForm": false,
        "inIndex": false,
        "inView": false
    },
    {
        "name": "updated_at",
        "dbType": "datetime",
        "htmlType": "date",
        "validations": "nullable|nullable",
        "searchable": false,
        "fillable": false,
        "primary": false,
        "inForm": false,
        "inIndex": false,
        "inView": false
    }
]